LICENSE
MANIFEST.in
README.rst
setup.py
tox_envreport/__init__.py
tox_envreport/plugin.py
tox_envreport.egg-info/PKG-INFO
tox_envreport.egg-info/SOURCES.txt
tox_envreport.egg-info/dependency_links.txt
tox_envreport.egg-info/entry_points.txt
tox_envreport.egg-info/requires.txt
tox_envreport.egg-info/top_level.txt